apu_cas/__init__.py
apu_cas/service_ticket.py
apu_cas/user_cas_attributes.py
apu_cas/user_role.py
apu_cas/variables.py
apu_cas-0.2.2.dist-info/METADATA
apu_cas-0.2.2.dist-info/WHEEL
apu_cas-0.2.2.dist-info/top_level.txt
apu_cas-0.2.2.dist-info/RECORD
