Metadata-Version: 2.1
Name: apu-cas
Version: 0.2.2
Summary: apu_cas is a python package for authentication with Asia Pacific University's Central Authentication Service
Home-page: https://bitbucket.org/ctiteam/apu-cas-pip/
Author: Peu Wai Thian
Author-email: peu.waithian@staffemail.apu.edu.my
License: UNKNOWN
Platform: UNKNOWN
Classifier: Development Status :: 3 - Alpha
Classifier: Programming Language :: Python
Classifier: Programming Language :: Python :: 3.6
Classifier: Topic :: Software Development :: Libraries
Classifier: Topic :: Software Development :: Libraries :: Python Modules
Classifier: Intended Audience :: Developers
Requires-Python: >=3.6
Requires-Dist: Flask
Requires-Dist: requests
